PBC4cip/PBC4cip.CLI.py
PBC4cip/__init__.py
PBC4cip/core/Dataset.py
PBC4cip/core/DecisionTree.py
PBC4cip/core/DecisionTreeBuilder.py
PBC4cip/core/DistributionEvaluator.py
PBC4cip/core/DistributionEvaluatorHelper.py
PBC4cip/core/DistributionTester.py
PBC4cip/core/EmergingPatterns.py
PBC4cip/core/Evaluation.py
PBC4cip/core/EvaluationFunctionCombiner.py
PBC4cip/core/EvaluationFunctionCombinerRandom.py
PBC4cip/core/Feature.py
PBC4cip/core/FeatureSelectors.py
PBC4cip/core/FileManipulation.py
PBC4cip/core/FilteredCollection.py
PBC4cip/core/ForwardFeatureIterator.py
PBC4cip/core/Helpers.py
PBC4cip/core/Item.py
PBC4cip/core/PBC4cip.py
PBC4cip/core/PatternFilter.py
PBC4cip/core/PatternMiner.py
PBC4cip/core/RandomSampler.py
PBC4cip/core/ResultsAnalyzer.py
PBC4cip/core/SplitIterator.py
PBC4cip/core/SupervisedClassifier.py
PBC4cip/core/WinningSplitSelector.py
PBC4cip/core/__init__.py
PBC4cip/example/__init__.py
PBC4cip/example/example.py
PBC4cip-0.0.0.8.dist-info/LICENSE
PBC4cip-0.0.0.8.dist-info/METADATA
PBC4cip-0.0.0.8.dist-info/WHEEL
PBC4cip-0.0.0.8.dist-info/top_level.txt
PBC4cip-0.0.0.8.dist-info/RECORD
