Metadata-Version: 2.1
Name: PBC4cip
Version: 0.0.0.8
Summary: PBC4cip classifier for class imbalance problems
Home-page: https://github.com/octavioloyola/PBC4cip
Author: Ernesto Ramírez-Sáyago, Miguel Angel Medina-Pérez, Octavio Loyola-González
Author-email: A00513925@itesm.mx, migue@tec.mx, octavioloyola@tec.mx
License: UNKNOWN
Platform: UNKNOWN
Classifier: Programming Language :: Python :: 3
Classifier: License :: OSI Approved :: GNU General Public License (GPL)
Classifier: Operating System :: OS Independent
Requires-Python: >=3.6
Requires-Dist: numpy
Requires-Dist: pandas
Requires-Dist: scikit-learn
Requires-Dist: tqdm
